auth1api/__init__.py
auth1api/client.py
auth1api-1.0.0.dist-info/LICENSE
auth1api-1.0.0.dist-info/METADATA
auth1api-1.0.0.dist-info/WHEEL
auth1api-1.0.0.dist-info/top_level.txt
auth1api-1.0.0.dist-info/RECORD
