Metadata-Version: 2.1
Name: auth1api
Version: 1.0.0
Summary: A library to make requests to your Auth1 instance
Home-page: UNKNOWN
Author: Brian Li, Mark Lalor, and Yidi Huang
Author-email: auth1@case.edu
License: UNKNOWN
Platform: UNKNOWN
Classifier: Programming Language :: Python :: 3
Classifier: License :: OSI Approved :: MIT License
Classifier: Operating System :: OS Independent
Requires-Dist: requests
